[
null,
{"id":1,"battlerName":"Actor1_5","characterIndex":4,"characterName":"Actor1","classId":1,"equips":[1,1,2,3,0],"faceIndex":0,"faceName":"","traits":[],"initialLevel":1,"maxLevel":99,"name":"Bason","nickname":"","note":"","profile":""},
{"id":2,"battlerName":"fantabattler","characterIndex":0,"characterName":"fanta","classId":5,"equips":[3,0,0,0,0],"faceIndex":0,"faceName":"fanta","traits":[{"code":51,"dataId":6,"value":1},{"code":52,"dataId":2,"value":1},{"code":64,"dataId":4,"value":1}],"initialLevel":1,"maxLevel":99,"name":"Fanta","nickname":"","note":"","profile":"Cute, lively and adventurous. Having her in the party\ngives you double gold earnings!"}
]